chrysalis/__about__.py
chrysalis/__init__.py
chrysalis/execution.py
chrysalis/invariants.py
chrysalis/tables.py
chrysalis/_internal/__init__.py
chrysalis/_internal/conftest.py
chrysalis/_internal/controller.py
chrysalis/_internal/controller_test.py
chrysalis/_internal/engine.py
chrysalis/_internal/engine_test.py
chrysalis/_internal/invariants.py
chrysalis/_internal/invariants_test.py
chrysalis/_internal/search.py
chrysalis/_internal/search_test.py
chrysalis/_internal/writer.py
chrysalis/_internal/tables/defs.py
chrysalis/_internal/tables/defs_test.py
chrysalis/_internal/tables/relation.py
chrysalis/_internal/tables/relation_test.py
chrysalis/_internal/tables/replay.py
chrysalis/_internal/tables/replay_test.py
chrysalis_test-0.1.2.dist-info/licenses/LICENSE
chrysalis_test-0.1.2.dist-info/METADATA
chrysalis_test-0.1.2.dist-info/WHEEL
chrysalis_test-0.1.2.dist-info/top_level.txt
chrysalis_test-0.1.2.dist-info/RECORD
