Metadata-Version: 2.4
Name: chrysalis-test
Version: 0.1.2
Summary: A metamorphic testing framework for Python
Author-email: Nathan Huey <nathanhuey44@gmail.com>, Jai Parera <jaiparera@gmail.com>
License: MIT
Requires-Python: >=3.12
License-File: LICENSE
Requires-Dist: pytest>=8.0.0
Requires-Dist: duckdb>=1.2.0
Requires-Dist: tqdm>=4.67.1
Requires-Dist: types-tqdm>=4.67.0.20250809
Dynamic: license-file
